fabricatio_novel-0.1.9.dist-info/METADATA
fabricatio_novel-0.1.9.dist-info/WHEEL
fabricatio_novel-0.1.9.dist-info/entry_points.txt
fabricatio_novel/__init__.py
fabricatio_novel/actions/__init__.py
fabricatio_novel/actions/novel.py
fabricatio_novel/capabilities/__init__.py
fabricatio_novel/capabilities/novel.py
fabricatio_novel/cli.py
fabricatio_novel/config.py
fabricatio_novel/models/__init__.py
fabricatio_novel/models/novel.py
fabricatio_novel/models/scripting.py
fabricatio_novel/py.typed
fabricatio_novel/rust.cp312-win_amd64.pyd
fabricatio_novel/rust.pyi
fabricatio_novel/workflows/__init__.py
fabricatio_novel/workflows/novel.py
fabricatio_novel-0.1.9.dist-info/RECORD
