Metadata-Version: 2.4
Name: fabricatio-novel
Version: 0.1.9
Classifier: License :: OSI Approved :: MIT License
Classifier: Programming Language :: Python :: 3.12
Classifier: Programming Language :: Python :: 3.13
Classifier: Programming Language :: Python :: 3.14
Classifier: Programming Language :: Python :: Implementation :: CPython
Classifier: Typing :: Typed
Requires-Dist: fabricatio-character
Requires-Dist: fabricatio-core
Requires-Dist: pydantic>=2.11.9
Requires-Dist: fabricatio-novel[workflows,cli] ; extra == 'full'
Requires-Dist: fabricatio-actions ; extra == 'workflows'
Requires-Dist: fabricatio-novel[workflows] ; extra == 'cli'
Requires-Dist: questionary>=2.1.0 ; extra == 'cli'
Requires-Dist: typer-slim[standard]>=0.15.2 ; extra == 'cli'
Provides-Extra: full
Provides-Extra: workflows
Provides-Extra: cli
Summary: An extension of fabricatio
Author-email: Whth <zettainspector@foxmail.com>
License-Expression: MIT
Requires-Python: >=3.12, <3.15
Project-URL: Homepage, https://github.com/Whth/fabricatio
Project-URL: Repository, https://github.com/Whth/fabricatio
Project-URL: Issues, https://github.com/Whth/fabricatio/issues
